{
    "content": {
        "Methods": {
            "_updateSize": {
                "internal": true, 
                "text": "@private"
            }, 
            "getTag": {
                "internal": true, 
                "text": "@private"
            }, 
            "onAllowFullScreenChanged": {
                "internal": true, 
                "text": "@private"
            }, 
            "onSourceChanged": {
                "internal": true, 
                "text": "@private"
            }, 
            "onWidthChanged": {
                "internal": true, 
                "text": "@private"
            }
        }, 
        "Properties": {
            "allowFullScreen": {
                "internal": false, 
                "text": "allow fullscreen flag"
            }, 
            "source": {
                "internal": false, 
                "text": "video source URL"
            }
        }
    }, 
    "name": "controls.google.YouTube", 
    "text": "item for embedded youtube video"
}