{
    "content": {
        "Methods": {
            "onHeightChanged": {
                "internal": false, 
                "text": ""
            }, 
            "show": {
                "internal": false, 
                "text": ""
            }
        }, 
        "Properties": {
            "animationDuration": {
                "internal": false, 
                "text": ""
            }, 
            "barColor": {
                "internal": false, 
                "text": ""
            }, 
            "contentHeight": {
                "internal": false, 
                "text": ""
            }, 
            "contentY": {
                "internal": false, 
                "text": ""
            }, 
            "display": {
                "internal": false, 
                "text": ""
            }, 
            "displayHeight": {
                "internal": false, 
                "text": ""
            }, 
            "displaySeconds": {
                "internal": false, 
                "text": ""
            }, 
            "maxContentY": {
                "internal": false, 
                "text": ""
            }, 
            "minHeight": {
                "internal": false, 
                "text": ""
            }, 
            "realContentY": {
                "internal": false, 
                "text": ""
            }, 
            "realHeight": {
                "internal": false, 
                "text": ""
            }, 
            "shift": {
                "internal": false, 
                "text": ""
            }
        }
    }, 
    "name": "controls.pure.ScrollBar", 
    "text": ""
}