{
    "content": {
        "Alias Properties": {
            "hover": {
                "internal": false, 
                "text": "containsMouse property alias"
            }, 
            "hoverable": {
                "internal": false, 
                "text": "hoverEnabled property alias"
            }
        }, 
        "Methods": {
            "_bindClick": {
                "internal": true, 
                "text": "@private"
            }, 
            "_bindHover": {
                "internal": true, 
                "text": "@private"
            }, 
            "_bindPressable": {
                "internal": true, 
                "text": "@private"
            }, 
            "_bindTouch": {
                "internal": true, 
                "text": "@private"
            }, 
            "_bindWheel": {
                "internal": true, 
                "text": "@private"
            }, 
            "constructor": {
                "internal": true, 
                "text": "@private"
            }, 
            "onClickableChanged": {
                "internal": true, 
                "text": "@private"
            }, 
            "onContainsMouseChanged": {
                "internal": true, 
                "text": "@private"
            }, 
            "onCursorChanged": {
                "internal": true, 
                "text": "@private"
            }, 
            "onHoverEnabledChanged": {
                "internal": true, 
                "text": "@private"
            }, 
            "onMouseXChanged": {
                "internal": false, 
                "text": ""
            }, 
            "onMouseYChanged": {
                "internal": false, 
                "text": ""
            }, 
            "onPressableChanged": {
                "internal": true, 
                "text": "@private"
            }, 
            "onRecursiveVisibleChanged": {
                "internal": true, 
                "text": "@private"
            }, 
            "onTouchEnabledChanged": {
                "internal": true, 
                "text": "@private"
            }, 
            "onTouchMove": {
                "internal": true, 
                "text": "@private"
            }, 
            "onTouchStart": {
                "internal": true, 
                "text": "@private"
            }, 
            "onWheelEnabledChanged": {
                "internal": true, 
                "text": "@private"
            }, 
            "updatePosition": {
                "internal": true, 
                "text": "@private"
            }
        }, 
        "Properties": {
            "clickable": {
                "internal": false, 
                "text": "enable mouse click event handling flag"
            }, 
            "containsMouse": {
                "internal": false, 
                "text": "mouse inside item's area flag"
            }, 
            "cursor": {
                "internal": false, 
                "text": "mouse cursor inside the item's area"
            }, 
            "hoverEnabled": {
                "internal": false, 
                "text": "enable mouse hover event handling flag"
            }, 
            "mouseX": {
                "internal": false, 
                "text": "mouse x coordinate"
            }, 
            "mouseY": {
                "internal": false, 
                "text": "mouse y coordinate"
            }, 
            "pressable": {
                "internal": false, 
                "text": "enable mouse click event handling flag"
            }, 
            "pressed": {
                "internal": false, 
                "text": "mouse pressed flag"
            }, 
            "touchEnabled": {
                "internal": false, 
                "text": "enable touch events handling flag"
            }, 
            "wheelEnabled": {
                "internal": false, 
                "text": "enable mouse click event handling flag"
            }
        }, 
        "Signals": {
            "canceled": {
                "internal": false, 
                "text": "emitted when mouse leaved the item's area while mouse button was pressed"
            }, 
            "clicked": {
                "internal": false, 
                "text": "emitted on mouse click"
            }, 
            "entered": {
                "internal": false, 
                "text": "emitted when mouse entered the item's area"
            }, 
            "exited": {
                "internal": false, 
                "text": "emitted when mouse leaved the item's area"
            }, 
            "horizontalSwiped": {
                "internal": false, 
                "text": "emitted on horizontal swipe"
            }, 
            "mouseMove": {
                "internal": false, 
                "text": "emitted on mouse moved inside the item's area"
            }, 
            "touchEnd": {
                "internal": false, 
                "text": "emitted on touch event end"
            }, 
            "touchMove": {
                "internal": false, 
                "text": "emitted on mouse move while touching"
            }, 
            "touchStart": {
                "internal": false, 
                "text": "emitted on touch event start"
            }, 
            "verticalSwiped": {
                "internal": false, 
                "text": "emitted on vertical swipe"
            }, 
            "wheelEvent": {
                "internal": false, 
                "text": "emitted when mouse wheel scrolling"
            }
        }
    }, 
    "name": "core.MouseArea", 
    "text": "item provide mouse and touch events API"
}