{
    "content": {
        "Methods": {
            "_restart": {
                "internal": true, 
                "params": [], 
                "text": "@private"
            }, 
            "constructor": {
                "internal": true, 
                "text": ""
            }, 
            "onCompleted": {
                "internal": true, 
                "params": [], 
                "text": "@private"
            }, 
            "onIntervalChanged": {
                "internal": true, 
                "text": ""
            }, 
            "onRunningChanged": {
                "internal": true, 
                "text": ""
            }, 
            "onTriggered": {
                "internal": true, 
                "params": [], 
                "text": "@private"
            }, 
            "restart": {
                "internal": false, 
                "params": [], 
                "text": "restart timer, activate if stopped"
            }, 
            "start": {
                "internal": false, 
                "params": [], 
                "text": "starts timer"
            }, 
            "stop": {
                "internal": false, 
                "params": [], 
                "text": "stops timer"
            }
        }, 
        "Properties": {
            "interval": {
                "defaultValue": "1000", 
                "internal": false, 
                "text": "interval, ms", 
                "type": "int"
            }, 
            "repeat": {
                "defaultValue": "", 
                "internal": false, 
                "text": "makes this timer periodic", 
                "type": "bool"
            }, 
            "running": {
                "defaultValue": "", 
                "internal": false, 
                "text": "current timer status, true - running, false - paused", 
                "type": "bool"
            }, 
            "triggeredOnStart": {
                "defaultValue": "", 
                "internal": false, 
                "text": "fire timer's signal on start or activation", 
                "type": "bool"
            }
        }, 
        "Signals": {
            "triggered": {
                "internal": false, 
                "text": "this signal triggered when timer fires"
            }
        }
    }, 
    "name": "core.Timer", 
    "text": "class handles periodic tasks"
}