{
	"name": "core.Context",
	"text": "root item",

	"content": {
		"Properties": {
			"scrollY": { "text": "scrolled page vertical offset value", "internal": false, "type": "int", "defaultValue": "" },
			"keyProcessDelay": { "text": "key pressed handling delay timeout in millisecnods", "internal": false, "type": "int", "defaultValue": "" },
			"fullscreen": { "text": "fullscreen mode enabled / disabled", "internal": false, "type": "bool", "defaultValue": "" },
			"language": { "text": "localisation language", "internal": false, "type": "string", "defaultValue": "" },
			"system": { "text": "system info object", "ref": "qmlcore.core/System", "internal": false, "type": "System", "defaultValue": "System" },
			"location": { "text": "web-page location object", "ref": "qmlcore.core/Location", "internal": false, "type": "Location", "defaultValue": "Location" },
			"stylesheet": { "text": "@private", "ref": "qmlcore.platform.html5/Stylesheet", "internal": true, "type": "Stylesheet", "defaultValue": "Stylesheet" },
			"buildIdentifier": { "text": "@private", "internal": true, "type": "string", "defaultValue": "Powered by PureQML No-Partnership Edition Engine" },
			"virtualWidth": { "text": "virtual viewport width", "internal": false, "type": "int", "defaultValue": "${manifest.virtual.width}" },
			"virtualHeight": { "text": "virtual viewport height", "internal": false, "type": "int", "defaultValue": "${manifest.virtual.height}" },
			"virtualScale": { "text": "@private", "internal": true, "type": "real", "defaultValue": "Math.min(((${system.resolutionWidth} || ${width}) / ${virtualWidth}),((${system.resolutionHeight} || ${height}) / ${virtualHeight}))" }
		},

		"Methods": {
			"constructor": { "text": "@private", "params": [], "internal": true },
			"mangleClass": { "text": "@private", "params": [], "internal": true },
			"registerStyle": { "text": "@private", "params": [], "internal": true },
			"createElement": { "text": "@private", "params": [], "internal": true },
			"_init": { "text": "@private", "params": [], "internal": true },
			"init": { "text": "@private", "params": [], "internal": true },
			"__onCompleted": { "text": "@private", "params": [], "internal": true },
			"onFullscreenChanged": { "text": "", "internal": true },
			"scheduleComplete": { "text": "@internal", "params": [], "internal": true },
			"start": { "text": "@private", "params": [], "internal": true },
			"wrapNativeCallback": { "text": "", "internal": false },
			"_processActions": { "text": "if you need to call it from native callback, use wrapNativeCallback method", "params": [], "internal": false },
			"scheduleAction": { "text": "@private", "params": [], "internal": true },
			"delayedAction": { "text": "@private", "params": [], "internal": true },
			"qsTr": { "text": "Returns input text translation", "params": [{ "name": "text", "type": "string", "text": "text that must be translated" }], "internal": false },
			"tr": { "text": "", "internal": false },
			"updateL10n": { "text": "", "internal": false },
			"processKey": { "text": "", "internal": false },
			"run": { "text": "@private", "params": [], "internal": true },
			"_run": { "text": "@private", "params": [], "internal": true }
		}
	}
}