{
    "content": {
        "Methods": {
            "onCompleted": {
                "internal": true,
                "text": ""
            }
        },
        "Properties": {
            "mobileMode": {
                "defaultValue": "${menu.rowsCount} > 1",
                "internal": false,
                "text": "",
                "type": "bool"
            },
            "newWindow": {
                "defaultValue": "",
                "internal": false,
                "text": "",
                "type": "bool"
            },
            "open": {
                "defaultValue": "",
                "internal": false,
                "text": "",
                "type": "bool"
            }
        }
    },
    "name": "src.Head",
    "text": ""
}